setup.cfg
setup.py
xwot_yadp.egg-info/PKG-INFO
xwot_yadp.egg-info/SOURCES.txt
xwot_yadp.egg-info/dependency_links.txt
xwot_yadp.egg-info/entry_points.txt
xwot_yadp.egg-info/requires.txt
xwot_yadp.egg-info/top_level.txt
yadp/__init__.py
yadp/cmd.py
yadp/device.py
yadp/multithreading.py
yadp/core/__init__.py
yadp/core/constant.py
yadp/core/device.py
yadp/core/message.py
yadp/core/multicast.py
yadp/core/unicast.py
yadp/core/urn_matcher.py
yadp/semantic/__init__.py
yadp/semantic/core.py
yadp/semantic/resource.py
yadp/semantic/vocab.py
yadp/twisted/__init__.py
yadp/twisted/adapter/__init__.py
yadp/twisted/adapter/multicast.py
yadp/twisted/adapter/unicast.py
yadp/util/__init__.py
yadp/util/vsm.py
yadp/util/web.py