Metadata-Version: 1.1
Name: xwot-yadp
Version: 1.0.1
Summary: Yet Another Discovery Protocol
Home-page: https://github.com/lexruee/yadp
Author: Alexander Rüedlinger
Author-email: a.rueedlinger@gmail.com
License: AGPL v3
Platform: UNKNOWN
Classifier: License :: OSI Approved :: GNU Affero General Public License v3
